<?xml version = '1.0' encoding = 'UTF-8'?>
<FKIndexAssociation class="oracle.dbtools.crest.model.design.relational.FKIndexAssociation" directorySegmentName="seg_1" id="57960A17-555E-9BC3-A341-53BFEA18803D" containerWithKeyObject="119DB342-8FE6-7C43-8C6E-0997CE18F1C8" localFKIndex="C44AC3CD-1F6B-8E69-F8F9-0B529C4FD034" name="PRS_PAL_PK_PN">
<sourceConnName>ADMT</sourceConnName>
<sourceObjSchema>PRSDBM</sourceObjSchema>
<sourceObjName>PRS_PAL_PK_PN</sourceObjName>
<createdBy>niluc</createdBy>
<createdTime>2020-07-28 19:07:59 UTC</createdTime>
<ownerDesignName>PRS</ownerDesignName>
<importedID>DEE1F0CA-BC5A-6D73-F68A-B6E3EA65D0ED</importedID>
<referredTableLongName>PRS_PURCHASE_REQ</referredTableLongName>
<deleteRule>NO ACTION</deleteRule>
<referredTableID>0ACC5942-7486-7DFC-ED54-80748B3CDA76</referredTableID>
<keyObject>976FD90E-A521-8C8A-03CC-5A2CFD46AA71</keyObject>
<referredKeyID>976FD90E-A521-8C8A-03CC-5A2CFD46AA71</referredKeyID>
<mandatory>true</mandatory>
<refColNames>PR_N</refColNames>
<transferable>true</transferable>
<rely>false</rely>
<columnDependencyConstraintGenerateInDDL>true</columnDependencyConstraintGenerateInDDL>
</FKIndexAssociation>